AUTHORS
LICENSE.txt
MANIFEST.in
README.rst
setup.cfg
setup.py
levmar/__init__.py
levmar/_config.py
levmar/_levmar.c
levmar/_release.py
levmar.egg-info/PKG-INFO
levmar.egg-info/SOURCES.txt
levmar.egg-info/dependency_links.txt
levmar.egg-info/not-zip-safe
levmar.egg-info/requires.txt
levmar.egg-info/top_level.txt
levmar/levmar-2.6/Axb.c
levmar/levmar-2.6/Axb_core.c
levmar/levmar-2.6/compiler.h
levmar/levmar-2.6/expfit.c
levmar/levmar-2.6/levmar.h
levmar/levmar-2.6/lm.c
levmar/levmar-2.6/lm.h
levmar/levmar-2.6/lm_core.c
levmar/levmar-2.6/lmbc.c
levmar/levmar-2.6/lmbc_core.c
levmar/levmar-2.6/lmblec.c
levmar/levmar-2.6/lmblec_core.c
levmar/levmar-2.6/lmbleic.c
levmar/levmar-2.6/lmbleic_core.c
levmar/levmar-2.6/lmdemo.c
levmar/levmar-2.6/lmlec.c
levmar/levmar-2.6/lmlec_core.c
levmar/levmar-2.6/misc.c
levmar/levmar-2.6/misc.h
levmar/levmar-2.6/misc_core.c
levmar/tests/__init__.py
levmar/tests/test_levmar.py