Metadata-Version: 1.1
Name: levmar
Version: 0.2.2
Summary: Python binding to the levmar library using Cython.
Home-page: https://github.com/bjodah/levmar
Author: Björn Dahlgren
Author-email: bjodah@gmail.com
License: GNU General Public Licence v2
Platform: UNKNOWN
Classifier: Intended Audience :: Science/Research
Classifier: Topic :: Scientific/Engineering
Classifier: Topic :: Scientific/Engineering :: Mathematics
Classifier: Programming Language :: Python
Classifier: Programming Language :: Python :: 2
Classifier: Programming Language :: Python :: 2.7
Classifier: Programming Language :: Python :: 3
Classifier: Programming Language :: Python :: 3.4
Classifier: Programming Language :: Python :: 3.5
Classifier: License :: OSI Approved :: MIT License
